dv_charts/BarDrawer.py
dv_charts/BarRender.py
dv_charts/BoxDrawer.py
dv_charts/BoxRender.py
dv_charts/CorrDrawer.py
dv_charts/CorrRender.py
dv_charts/DesDrawer.py
dv_charts/DesRender.py
dv_charts/DvCharts.py
dv_charts/DvpBar.py
dv_charts/DvpBox.py
dv_charts/DvpCatStats.py
dv_charts/DvpCorr.py
dv_charts/DvpDashboard.py
dv_charts/DvpDesBar.py
dv_charts/DvpDesBox.py
dv_charts/DvpDesCorr.py
dv_charts/DvpDesHistogram.py
dv_charts/DvpDesPie.py
dv_charts/DvpDesScatter.py
dv_charts/DvpHistogram.py
dv_charts/DvpNumStats.py
dv_charts/DvpPie.py
dv_charts/DvpScatter.py
dv_charts/DvpStyle.py
dv_charts/DvpTextRender.py
dv_charts/DvpWordCloud.py
dv_charts/DvpWordGraph.py
dv_charts/HistDrawer.py
dv_charts/HistRender.py
dv_charts/LineDrawer.py
dv_charts/PieDrawer.py
dv_charts/PieRender.py
dv_charts/ScatterDrawer.py
dv_charts/ScatterRender.py
dv_charts/TextDrawer.py
dv_charts/Theme.py
dv_charts/__init__.py
dv_charts/_imports_.py
dv_charts/async-DvCharts.js
dv_charts/async-DvCharts.js.map
dv_charts/dv_charts.min.js
dv_charts/dv_charts.min.js.map
dv_charts/metadata.json
dv_charts/package-info.json
dv_charts-0.1.1.dist-info/LICENSE
dv_charts-0.1.1.dist-info/METADATA
dv_charts-0.1.1.dist-info/WHEEL
dv_charts-0.1.1.dist-info/top_level.txt
dv_charts-0.1.1.dist-info/RECORD
